quade/__init__.py
quade/admin.py
quade/apps.py
quade/compatability.py
quade/fixtures.py
quade/managers.py
quade/models.py
quade/receivers.py
quade/settings.py
quade/tasks.py
quade/urls.py
quade/views.py
quade/jinja2/quade/main.jinja
quade/management/__init__.py
quade/management/commands/__init__.py
quade/management/commands/list_fixtures.py
quade/migrations/0001_initial.py
quade/migrations/__init__.py
quade/templatetags/__init__.py
quade/templatetags/qa_extras.py
quade-0.2.2.dist-info/DESCRIPTION.rst
quade-0.2.2.dist-info/METADATA
quade-0.2.2.dist-info/RECORD
quade-0.2.2.dist-info/WHEEL
quade-0.2.2.dist-info/metadata.json
quade-0.2.2.dist-info/top_level.txt
