Metadata-Version: 2.0
Name: quade
Version: 0.2.2
Summary: The friendly QA tool for Django.
Home-page: https://github.com/makingspace/quade
Author: Paul Baranay
Author-email: pbaranay@makespace.com
License: MIT
Keywords: django
Platform: UNKNOWN
Classifier: Development Status :: 3 - Alpha
Classifier: Framework :: Django
Classifier: Framework :: Django :: 1.8
Classifier: Framework :: Django :: 1.9
Classifier: Framework :: Django :: 1.10
Classifier: Framework :: Django :: 1.11
Classifier: Framework :: Django :: 2.0
Classifier: Intended Audience :: Developers
Classifier: License :: OSI Approved :: BSD License
Classifier: Programming Language :: Python :: 2
Classifier: Programming Language :: Python :: 2.7
Classifier: Programming Language :: Python :: 3
Classifier: Programming Language :: Python :: 3.3
Classifier: Programming Language :: Python :: 3.4
Classifier: Programming Language :: Python :: 3.5
Classifier: Programming Language :: Python :: 3.6
Requires-Dist: attrs
Requires-Dist: django-fsm (==1.6)
Requires-Dist: django-light-enums
Requires-Dist: django-jinja
Requires-Dist: future
Requires-Dist: jsonfield
Provides-Extra: celery
Requires-Dist: celery; extra == 'celery'
